unit_text/__init__.py
unit_text/__main__.py
unit_text/api/__init__.py
unit_text/api/__main__.py
unit_text/api/app.py
unit_text/api/server.py
unit_text/cli/__init__.py
unit_text/cli/app.py
unit_text/core/__init__.py
unit_text/core/lib.py
unit_text/core/models.py
unit_text-0.3.0.dist-info/METADATA
unit_text-0.3.0.dist-info/WHEEL
unit_text-0.3.0.dist-info/entry_points.txt
unit_text-0.3.0.dist-info/licenses/LICENSE
unit_text-0.3.0.dist-info/RECORD
