Metadata-Version: 2.4
Name: unit-text
Version: 0.3.0
Summary: Unit tests for plain text
Project-URL: source, https://github.com/sealambda/unit-text
Project-URL: issues, https://github.com/sealambda/unit-text/issues
Author-email: Giorgio Azzinnaro <giorgio.azzinnaro@sealambda.com>, Sealambda <hello@sealambda.com>
License-Expression: AGPL-3.0-or-later
License-File: LICENSE
Keywords: ai,blog,cli,editor,language,llm,ollama,test,unit
Classifier: Development Status :: 4 - Beta
Classifier: Environment :: Console
Classifier: Intended Audience :: Developers
Classifier: Intended Audience :: Other Audience
Classifier: License :: OSI Approved :: GNU Affero General Public License v3 or later (AGPLv3+)
Classifier: Natural Language :: English
Classifier: Operating System :: OS Independent
Classifier: Programming Language :: Python :: 3.11
Classifier: Programming Language :: Python :: 3.12
Classifier: Programming Language :: Python :: 3.13
Classifier: Topic :: Text Editors
Classifier: Topic :: Text Editors :: Text Processing
Classifier: Topic :: Text Processing :: General
Classifier: Topic :: Text Processing :: Linguistic
Classifier: Topic :: Utilities
Requires-Python: >=3.11
Requires-Dist: dicttoxml>=1.7.16
Requires-Dist: fastapi[standard]>=0.115.11
Requires-Dist: ollama>=0.4.7
Requires-Dist: pydantic>=2.10.6
Requires-Dist: rich
Requires-Dist: typer>=0.15.1
